async_downloads/__init__.py
async_downloads/apps.py
async_downloads/cache.py
async_downloads/settings.py
async_downloads/shortcuts.py
async_downloads/tasks.py
async_downloads/urls.py
async_downloads/views.py
async_downloads/ws_consumers.py
async_downloads/static/css/async_downloads.css
async_downloads/static/js/async_downloads.js
async_downloads/static/js/ws_async_downloads.js
async_downloads/templates/async_downloads/download_centre.html
async_downloads/templates/async_downloads/downloads.html
django_async_downloads-0.6.0.dist-info/LICENSE
django_async_downloads-0.6.0.dist-info/METADATA
django_async_downloads-0.6.0.dist-info/WHEEL
django_async_downloads-0.6.0.dist-info/top_level.txt
django_async_downloads-0.6.0.dist-info/RECORD
