Metadata-Version: 2.1
Name: django-async-downloads
Version: 0.6.0
Summary: Asynchronous downloads scaffolding for Django projects
Home-page: https://github.com/QuickRelease/django-async-downloads.git
Author: David Vaughan
Author-email: david.vaughan@quickrelease.co.uk
Maintainer: Quick Release (Automotive) Ltd.
License: MIT
Keywords: django download asynchronous async celery
Classifier: Programming Language :: Python :: 3
Classifier: Framework :: Django :: 2.0
Classifier: Framework :: Django :: 2.1
Classifier: Framework :: Django :: 2.2
Classifier: Framework :: Django :: 3.0
Classifier: Framework :: Django :: 3.1
Classifier: Framework :: Django :: 3.2
Classifier: License :: OSI Approved :: MIT License
Classifier: Intended Audience :: Developers
Classifier: Operating System :: OS Independent
License-File: LICENSE
Requires-Dist: Django>=2.0
Requires-Dist: celery>=4.2.1
Requires-Dist: pathvalidate>=2.3.0
Provides-Extra: ws
Requires-Dist: channels>=3.0; extra == "ws"
Requires-Dist: channels_redis>=3.0; extra == "ws"
